src/__init__.py
src/main.py
src/vue/__init__.py
src/vue/boiler_playes.py
viquick-0.1.2.dist-info/METADATA
viquick-0.1.2.dist-info/WHEEL
viquick-0.1.2.dist-info/entry_points.txt
viquick-0.1.2.dist-info/top_level.txt
viquick-0.1.2.dist-info/RECORD
