Metadata-Version: 2.4
Name: viquick
Version: 0.1.2
Summary: CLI tool that speeds up development
Requires-Python: >=3.12
Requires-Dist: questionary>=2.1.0
Requires-Dist: rich>=14.0.0
Requires-Dist: typer>=0.16.0
